 [
  {
    "name": "Panthers Jersey",
    "sizes": [
      { "size": "S", "additionalPrice": 0 },
      { "size": "M", "additionalPrice": 2 },
      { "size": "L", "additionalPrice": 4 },
      { "size": "XL", "additionalPrice": 6 }
    ],
    "price": 25.99,
    "images": [{ "url": "https://example.com/panthers_jersey.jpg" }],
    "customizations": [
      { "title": "Player Name", "price": 5 },
      { "title": "Number", "price": 3 }
    ],
    "sizeChart": "https://example.com/panthers_size_chart.jpg",
    "category": "64e4027263cb4d4bc34e2067",
    "store": "614f4c3eebd6b9e9d6aa4563"
  }
]
